lwjs/__init__.py
lwjs/core/__init__.py
lwjs/core/bone.py
lwjs/core/chop.py
lwjs/core/cook.py
lwjs/core/help.py
lwjs/funs/__init__.py
lwjs/funs/calc.py
lwjs/funs/date.py
lwjs/funs/dump.py
lwjs/funs/env.py
lwjs/funs/false.py
lwjs/funs/json.py
lwjs/funs/map.py
lwjs/funs/nvl.py
lwjs/funs/read.py
lwjs/funs/true.py
lwjs/funs/void.py
lwjs-1.0.0.dist-info/METADATA
lwjs-1.0.0.dist-info/WHEEL
lwjs-1.0.0.dist-info/licenses/LICENSE.md
lwjs-1.0.0.dist-info/RECORD
