Metadata-Version: 2.1
Name: lwjs
Version: 1.0.0
Summary: Light Weight JSON Shell
Project-URL: Homepage, https://github.com/andreihes/lwjs
Project-URL: Bug Tracker, https://github.com/andreihes/lwjs/issues
Author-email: Andrei Hes <andrei.hes@ya.ru>
License-Expression: WTFPL
License-File: LICENSE.md
Classifier: Operating System :: OS Independent
Classifier: Programming Language :: Python :: 3
Requires-Python: >=3.10
